{"Breadcrumb List Schema":{"prefix":"breadcrumb-list-schema","description":"Breadcrumb List Schema","body":["{","\t\"@context\": \"http://schema.org\",","\t\"@type\": \"BreadcrumbList\",","\t\"itemListElement\": [{","\t\t\"@type\": \"ListItem\",","\t\t\"position\": 1,","\t\t\"name\": \"${1:item-1-name}\",","\t\t\"item\": \"${2:item-1-url}\"","\t},{","\t\t\"@type\": \"ListItem\",","\t\t\"position\": 2,","\t\t\"name\": \"${3:item-2-name}\",","\t\t\"item\": \"${4:item-2-url}\"","\t},{","\t\t\"@type\": \"ListItem\",","\t\t\"position\": 3,","\t\t\"name\": \"${5:item-3-name}\",","\t\t\"item\": \"${6:item-3-url}\"","\t}]","}"]},"Corporate Contact Schema":{"prefix":"corporate-contact-schema","description":"Corporate Contact Schema","body":["{","\t\"@context\": \"http://schema.org\",","\t\"@type\": \"Organization\",","\t\"url\": \"${1:website-url}\",","\t\"contactPoint\": [{","\t\t\"@type\": \"ContactPoint\",","\t\t\"telephone\": \"${2:+1-234-567-8910}\",","\t\t\"contactType\": \"${3|customer support,technical support,billing support,bill payment,sales,reservations,credit card support,emergency,baggage tracking,roadside assistance,package tracking|}\",","\t\t\"contactOption\": \"${4|TollFree,HearingImpairedSupported|}\",","\t\t\"areaServed\": [","\t\t\t\"${5:US}\"","\t\t],","\t\t\"availableLanguage\": [","\t\t\t\"${6:English}\"","\t\t]","\t}]","}"]},"Event Schema":{"prefix":"event-schema","description":"Event Schema","body":["{","\t\"@context\": \"http://schema.org\",","\t\"@type\": \"Event\",","\t\"name\": \"${1:event-name}\",","\t\"description\": \"${2:video-description}\",","\t\"startDate\": \"${3:yyyy-mm-dd}T${4:hh:mm}\",","\t\"endDate\": \"${5:yyyy-mm-dd}T${6:hh:mm}\",","\t\"location\": {","\t\t\"@type\": \"Place\",","\t\t\"name\": \"${7:place-name}\",","\t\t\"address\": {","\t\t\t\"@type\": \"PostalAddress\",","\t\t\t\"streetAddress\": \"${8:address}\",","\t\t\t\"addressLocality\": \"${9:city}\",","\t\t\t\"postalCode\": \"${10:postal-code}\",","\t\t\t\"addressRegion\": \"${11:state}\",","\t\t\t\"addressCountry\": \"${12:country}\"","\t\t}","\t},","\t\"image\": [","\t\t\"${13:https://example.com/photos/1x1/photo.jpg}\",","\t\t\"${14:https://example.com/photos/4x3/photo.jpg}\",","\t\t\"${15:https://example.com/photos/16x9/photo.jpg}\"","\t],","\t\"offers\": {","\t\t\"@type\": \"Offer\",","\t\t\"url\": \"${16:offer-url}\",","\t\t\"price\": \"${17:price}\",","\t\t\"priceCurrency\": \"${18:price-currency}\",","\t\t\"availability\": \"https://schema.org/${19|InStock,PreOrder,SoldOut|}\",","\t\t\"validFrom\": \"${20:yyyy-mm-dd}T${21:hh:mm}\"","\t},","\t\"performer\": {","\t\t\"@type\": \"PerformingGroup\",","\t\t\"name\": \"${22:performer-name}\"","\t}","}"]},"Job Posting Schema":{"prefix":"job-posting-schema","description":"Job Posting Schema","body":["{","\t\"@context\": \"http://schema.org\",","\t\"@type\": \"JobPosting\",","\t\"title\": \"${1:job-title}\",","\t\"description\": \"${2:job-description}\",","\t\"identifier\": {","\t\t\"@type\": \"PropertyValue\",","\t\t\"name\": \"${3:company-name}\",","\t\t\"value\": \"${4:unique-job-identifier}\",","\t},","\t\"datePosted\": \"${5:yyyy-mm-dd}\",","\t\"validThrough\": \"${6:yyyy-mm-dd}T${7:hh:mm}\",","\t\"employmentType\": \"${8|FULL_TIME,PART_TIME,CONTRACTOR,TEMPORARY,INTERN,VOLUNTEER,PER_DIEM,OTHER|}\",","\t\"hiringOrganization\": {","\t\t\"@type\": \"Organization\",","\t\t\"name\": \"${9:hiring-organization-name}\",","\t\t\"sameAs\": \"${10:hiring-organization-url}\",","\t\t\"logo\": \"${11:hiring-organization-logo-url}\"","\t},","\t\"jobLocation\": {","\t\t\"@type\": \"Place\",","\t\t\"address\": {","\t\t\t\"@type\": \"PostalAddress\",","\t\t\t\"streetAddress\": \"${12:street-address}\",","\t\t\t\"addressLocality\": \"${13:city}\",","\t\t\t\"addressRegion\": \"${14:state}\",","\t\t\t\"postalCode\": \"${15:postal-code}\",","\t\t\t\"addressCountry\": \"${16:country}\"","\t\t}","\t},","\"baseSalary\": {","\t\t\"@type\": \"MonetaryAmount\",","\t\t\"currency\": \"${17|AED,AFN,ALL,AMD,ANG,AOA,ARS,AUD,AWG,AZN,BAM,BBD,BDT,BGN,BHD,BIF,BMD,BND,BOB,BOV,BRL,BSD,BTN,BWP,BYN,BZD,CAD,CDF,CHE,CHF,CHW,CLF,CLP,CNY,COP,COU,CRC,CUC,CUP,CVE,CZK,DJF,DKK,DOP,DZD,EGP,ERN,ETB,EUR,FJD,FKP,GBP,GEL,GHS,GIP,GMD,GNF,GTQ,GYD,HKD,HNL,HRK,HTG,HUF,IDR,ILS,INR,IQD,IRR,ISK,JMD,JOD,JPY,KES,KGS,KHR,KMF,KPW,KRW,KWD,KYD,KZT,LAK,LBP,LKR,LRD,LSL,LYD,MAD,MDL,MGA,MKD,MMK,MNT,MOP,MRU,MUR,MVR,MWK,MXN,MXV,MYR,MZN,NAD,NGN,NIO,NOK,NPR,NZD,OMR,PAB,PEN,PGK,PHP,PKR,PLN,PYG,QAR,RON,RSD,RUB,RWF,SAR,SBD,SCR,SDG,SEK,SGD,SHP,SLL,SOS,SRD,SSP,STN,SVC,SYP,SZL,THB,TJS,TMT,TND,TOP,TRY,TTD,TWD,TZS,UAH,UGX,USD,USN,UYI,UYU,UYW,UZS,VES,VND,VUV,WST,XAF,XAG,XAU,XBA,XBB,XBC,XBD,XCD,XDR,XOF,XPD,XPF,XPT,XSU,XUA,YER,ZAR,ZMW,ZWL|}\",","\t\t\"value\": {","\t\t\t\"@type\": \"QuantitativeValue\",","\t\t\t\"value\": \"${18:value}\",","\t\t\t\"unitText\": \"${19:HOUR}\"","\t\t}","\t}","}"]},"Product Aggregate Offer Schema":{"prefix":"product-aggregate-offer-schema","description":"Product Aggregate Offer Schema","body":["{","\t\"@context\": \"http://schema.org\",","\t\"@type\": \"Product\",","\t\"name\": \"${1:product-name}\",","\t\"image\": [","\t\t\"${2:product-images}\"","\t],","\t\"brand\": {","\t\t\"@type\": \"Thing\",","\t\t\"name\": \"${3:product-brand}\"","\t},","\t\"aggregateRating\" : {","\t\t\"@type\": \"AggregateRating\",","\t\t\"ratingValue\": \"${4:rating-value}\",","\t\t\"reviewCount\": \"${5:review-count}\"","\t},","\t\"offers\": {","\t\t\"@type\": \"AggregateOffer\",","\t\t\"lowPrice\": \"${6:low-price}\",","\t\t\"highPrice\": \"${7:high-price}\",","\t\t\"priceCurrency\": \"${8|AED,AFN,ALL,AMD,ANG,AOA,ARS,AUD,AWG,AZN,BAM,BBD,BDT,BGN,BHD,BIF,BMD,BND,BOB,BOV,BRL,BSD,BTN,BWP,BYN,BZD,CAD,CDF,CHE,CHF,CHW,CLF,CLP,CNY,COP,COU,CRC,CUC,CUP,CVE,CZK,DJF,DKK,DOP,DZD,EGP,ERN,ETB,EUR,FJD,FKP,GBP,GEL,GHS,GIP,GMD,GNF,GTQ,GYD,HKD,HNL,HRK,HTG,HUF,IDR,ILS,INR,IQD,IRR,ISK,JMD,JOD,JPY,KES,KGS,KHR,KMF,KPW,KRW,KWD,KYD,KZT,LAK,LBP,LKR,LRD,LSL,LYD,MAD,MDL,MGA,MKD,MMK,MNT,MOP,MRU,MUR,MVR,MWK,MXN,MXV,MYR,MZN,NAD,NGN,NIO,NOK,NPR,NZD,OMR,PAB,PEN,PGK,PHP,PKR,PLN,PYG,QAR,RON,RSD,RUB,RWF,SAR,SBD,SCR,SDG,SEK,SGD,SHP,SLL,SOS,SRD,SSP,STN,SVC,SYP,SZL,THB,TJS,TMT,TND,TOP,TRY,TTD,TWD,TZS,UAH,UGX,USD,USN,UYI,UYU,UYW,UZS,VES,VND,VUV,WST,XAF,XAG,XAU,XBA,XBB,XBC,XBD,XCD,XDR,XOF,XPD,XPF,XPT,XSU,XUA,YER,ZAR,ZMW,ZWL|}\",","\t\t\"offerCount\": \"${9:offer-count}\",","\t}","}"]},"Product Schema":{"prefix":"product-schema","description":"Product Schema","body":["{","\t\"@context\": \"http://schema.org\",","\t\"@type\": \"Product\",","\t\"name\": \"${1:product-name}\",","\t\"image\": [","\t\t\"${2:product-images}\"","\t],","\t\"description\": \"${3:product-description}\",","\t\"${4|sku,gtin8,gtin13,gtin14,mpn|}\": \"${5:product-identifier}\",","\t\"brand\": {","\t\t\"@type\": \"Thing\",","\t\t\"name\": \"${6:product-brand}\"","\t},","\t\"aggregateRating\" : {","\t\t\"@type\": \"AggregateRating\",","\t\t\"ratingValue\": \"${7:rating-value}\",","\t\t\"reviewCount\": \"${8:review-count}\"","\t},","\t\"offers\": {","\t\t\"@type\": \"Offer\",","\t\t\"priceCurrency\": \"${9|AED,AFN,ALL,AMD,ANG,AOA,ARS,AUD,AWG,AZN,BAM,BBD,BDT,BGN,BHD,BIF,BMD,BND,BOB,BOV,BRL,BSD,BTN,BWP,BYN,BZD,CAD,CDF,CHE,CHF,CHW,CLF,CLP,CNY,COP,COU,CRC,CUC,CUP,CVE,CZK,DJF,DKK,DOP,DZD,EGP,ERN,ETB,EUR,FJD,FKP,GBP,GEL,GHS,GIP,GMD,GNF,GTQ,GYD,HKD,HNL,HRK,HTG,HUF,IDR,ILS,INR,IQD,IRR,ISK,JMD,JOD,JPY,KES,KGS,KHR,KMF,KPW,KRW,KWD,KYD,KZT,LAK,LBP,LKR,LRD,LSL,LYD,MAD,MDL,MGA,MKD,MMK,MNT,MOP,MRU,MUR,MVR,MWK,MXN,MXV,MYR,MZN,NAD,NGN,NIO,NOK,NPR,NZD,OMR,PAB,PEN,PGK,PHP,PKR,PLN,PYG,QAR,RON,RSD,RUB,RWF,SAR,SBD,SCR,SDG,SEK,SGD,SHP,SLL,SOS,SRD,SSP,STN,SVC,SYP,SZL,THB,TJS,TMT,TND,TOP,TRY,TTD,TWD,TZS,UAH,UGX,USD,USN,UYI,UYU,UYW,UZS,VES,VND,VUV,WST,XAF,XAG,XAU,XBA,XBB,XBC,XBD,XCD,XDR,XOF,XPD,XPF,XPT,XSU,XUA,YER,ZAR,ZMW,ZWL|}\",","\t\t\"price\": \"${10:price}\",","\t\t\"priceValidUntil\": \"${11:yyyy-mm-dd}\",","\t\t\"itemCondition\": \"https://schema.org/${12|DamagedCondition,NewCondition,RefurbishedCondition,UsedCondition|}\",","\t\t\"availability\": \"https://schema.org/${13|Discontinued,InStock,InStoreOnly,LimitedAvailability,OnlineOnly,OutOfStock,PreOrder,PreSale,SoldOut|}\",","\t\t\"seller\": {","\t\t\t\"@type\": \"Organization\",","\t\t\t\"name\": \"${14:organization-name}\",","\t\t},","\t\t\"url\": \"${15:offer-url}\"","\t}","}"]},"Recipe Schema":{"prefix":"recipe-schema","description":"Recipe Schema","body":["{","\t\"@context\": \"http://schema.org\",","\t\"@type\": \"Recipe\",","\t\"name\": \"${1:recipe-name}\",","\t\"description\": \"${2:recipe-description}\",","\t\"image\": [","\t\t\"${3:https://example.com/photos/1x1/photo.jpg}\",","\t\t\"${4:https://example.com/photos/4x3/photo.jpg}\",","\t\t\"${5:https://example.com/photos/16x9/photo.jpg}\"","\t],","\t\"author\": {","\t\t\"@type\": \"Person\",","\t\t\"name\": \"${6:name}\"","\t},","\t\"datePublished\": \"${7:yyyy-mm-dd}\",","\t\"prepTime\": \"${8:prep-time}\",","\t\"cookTime\": \"${9:cook-time}\",","\t\"totalTime\": \"${10:total-time}\",","\t\"keywords\": \"${11:keyword1, keyword2}\",","\t\"recipeYield\": \"${12:xx servings}\",","\t\"recipeCategory\": \"${13:dinner, entree, dessert, etc.}\",","\t\"recipeCuisine\": \"${14:French, Mediterranean, American, etc.}\",","\t\"nutrition\": {","\t\t\"@type\": \"NutritionInformation\",","\t\t\"calories\": \"${15:xx} calories\"","\t},","\t\"recipeIngredient\": [","\t\t\"${16:ingredient1}\",","\t\t\"${17:ingredient2}\",","\t\t\"${18:ingredient3}\"","\t],","\t\"recipeInstructions\": [","\t\t{","\t\t\t\"@type\": \"HowToStep\",","\t\t\t\"text\": \"${19:step1}\"","\t\t},","\t\t{","\t\t\t\"@type\": \"HowToStep\",","\t\t\t\"text\": \"${20:step2}\"","\t\t},","\t\t{","\t\t\t\"@type\": \"HowToStep\",","\t\t\t\"text\": \"${21:step3}\"","\t\t}","\t],","\t\"review\": [","\t\t{","\t\t\t\"@type\": \"Review\",","\t\t\t\"reviewRating\": {","\t\t\t\t\"@type\": \"Rating\",","\t\t\t\t\"ratingValue\": \"${22:average-rating}\",","\t\t\t\t\"bestRating\": \"${23:best-rating}\"","\t\t\t},","\t\t\t\"author\": {","\t\t\t\t\"@type\": \"Person\",","\t\t\t\t\"ratingValue\": \"${24:name}\"","\t\t\t},","\t\t\t\"datePublished\": \"${25:yyyy-mm-dd}\",","\t\t\t\"reviewBody\": \"${26:review-body}\",","\t\t\t\"publisher\": \"${27:publisher}\"","\t\t}","\t],","\t\"aggregateRating\": {","\t\t\"@type\": \"AggregateRating\",","\t\t\"ratingValue\": \"${28:average-rating}\",","\t\t\"ratingCount\": \"${29:ratings-count}\"","\t},","\t\"video\": [","\t\t${30:Type 'video-schema' and hit 'tab' or 'enter'}","\t]","}"]},"Sitelinks Searchbox Schema":{"prefix":"sitelinks-searchbox-schema","description":"Sitelinks Searchbox Schema","body":["{","\t\"@context\": \"http://schema.org\",","\t\"@type\": \"WebSite\",","\t\"url\": \"${1:website-url}\",","\t\"potentialAction\": {","\t\t\"@type\": \"SearchAction\",","\t\t\"target\": \"${2:https://query.example.com/search}?q={search_term_string}\",","\t\t\"query-input\": \"required name=search_term_string\"","\t}","}"]},"Video Schema":{"prefix":"video-schema","description":"Video Schema","body":["{","\t\"@context\": \"http://schema.org\",","\t\"@type\": \"VideoObject\",","\t\"name\": \"${1:video-name}\",","\t\"description\": \"${2:video-description}\",","\t\"thumbnailUrl\": [","\t\t\"${3:https://example.com/photos/1x1/photo.jpg}\",","\t\t\"${4:https://example.com/photos/4x3/photo.jpg}\",","\t\t\"${5:https://example.com/photos/16x9/photo.jpg}\"","\t],","\t\"uploadDate\": \"${6:yyyy-mm-dd}\",","\t\"duration\": \"${7:video-duration}\",","\t\"contentUrl\": \"${8:video-url}\",","\t\"embedUrl\": \"${9:embed-url}\",","\t\"interactionCount\": \"${10:interaction-count}\",","\t\"expires\": \"$${11:yyyy-mm-dd}\"","}"]},"Script JSON-LD":{"prefix":"script-json-ld","description":"Script JSON-LD","body":["<script type=\"application/ld+json\">","\t${1}","</script>"]}}